mlclouds/__init__.py
mlclouds/_version.py
mlclouds/autoxval.py
mlclouds/data_cleaners.py
mlclouds/data_handlers.py
mlclouds/grid_searcher.py
mlclouds/nsrdb.py
mlclouds/p_fun.py
mlclouds/tdhi.py
mlclouds/tdisc.py
mlclouds/tfarms.py
mlclouds/trainer.py
mlclouds/utilities.py
mlclouds/validator.py
mlclouds/model/__init__.py
mlclouds/model/base.py
mlclouds/model/multi_step.py
mlclouds/model/cloud_properties/config.json
mlclouds/model/cloud_properties/mlclouds_model.json
mlclouds/model/cloud_properties/mlclouds_model.pkl
mlclouds/model/cloud_properties/mlclouds_model_env.json
mlclouds/model/cloud_properties/training_history.csv
mlclouds/model/cloud_properties/validation_stats.csv
mlclouds/model/cloud_properties/validation_stats_east.csv
mlclouds/model/cloud_properties/validation_stats_west.csv
mlclouds/model/cloud_properties/outputs/mlclouds_model.json
mlclouds/model/cloud_properties/outputs/mlclouds_model.pkl
mlclouds/model/cloud_properties/outputs/mlclouds_model_env.json
mlclouds/model/cloud_properties/outputs/training_history.csv
mlclouds/model/cloud_properties/outputs/validation_stats.csv
mlclouds/model/cloud_properties/outputs/validation_stats_east.csv
mlclouds/model/cloud_properties/outputs/validation_stats_west.csv
mlclouds/model/cloud_type/config.json
mlclouds/model/cloud_type/outputs/mlclouds_model.json
mlclouds/model/cloud_type/outputs/mlclouds_model.pkl
mlclouds/model/cloud_type/outputs/mlclouds_model_env.json
mlclouds/model/cloud_type/outputs/training_history.csv
mlclouds/model/cloud_type/outputs/validation_stats.csv
mlclouds/model/cloud_type/outputs/validation_stats_east.csv
mlclouds/model/cloud_type/outputs/validation_stats_west.csv
mlclouds/model/k_fold/__init__.py
mlclouds/model/k_fold/config.json
mlclouds/model/k_fold/k_fold.py
mlclouds/model/k_fold/make_plots.py
mlclouds/model/k_fold/run_k_fold_all.sh
mlclouds/model/k_fold/run_k_fold_single.sh
mlclouds/model/k_fold/outputs/model_0.json
mlclouds/model/k_fold/outputs/model_0.pkl
NREL_mlclouds-0.0.5.dist-info/LICENSE
NREL_mlclouds-0.0.5.dist-info/METADATA
NREL_mlclouds-0.0.5.dist-info/WHEEL
NREL_mlclouds-0.0.5.dist-info/top_level.txt
NREL_mlclouds-0.0.5.dist-info/RECORD
