Metadata-Version: 2.1
Name: NREL-mlclouds
Version: 0.0.5
Summary: A machine learning approach to predicting missing cloud properties in the National Solar Radiation Database (mlclouds)
Author-email: Grant Buster <grant.buster@nrel.gov>, Brandon Benton <brandon.benton@nrel.gov>
License: BSD-3-Clause
Project-URL: homepage, https://github.com/NREL/mlclouds
Project-URL: documentation, https://nrel.github.io/mlclouds/
Project-URL: repository, https://github.com/NREL/mlclouds
Keywords: mlclouds,NREL
Classifier: Development Status :: 4 - Beta
Classifier: Intended Audience :: Science/Research
Classifier: License :: OSI Approved :: BSD License
Classifier: Natural Language :: English
Classifier: Programming Language :: Python :: 3.9
Classifier: Programming Language :: Python :: 3.10
Classifier: Programming Language :: Python :: 3.11
Requires-Python: >=3.9
License-File: LICENSE
Requires-Dist: NREL-nsrdb >=3.0
Requires-Dist: NREL-phygnn >=0.0.24
Requires-Dist: tensorflow ==2.12
Requires-Dist: plotly
Provides-Extra: dev
Requires-Dist: build >=0.5 ; extra == 'dev'
Requires-Dist: pre-commit ; extra == 'dev'
Requires-Dist: ruff >=0.5.0 ; extra == 'dev'
Provides-Extra: doc
Requires-Dist: sphinx >=7.0 ; extra == 'doc'
Requires-Dist: sphinx-rtd-theme >=2.0 ; extra == 'doc'
Requires-Dist: sphinx-click >=4.0 ; extra == 'doc'
Provides-Extra: test
Requires-Dist: pytest >=5.2 ; extra == 'test'
Requires-Dist: pytest-env >=1.1.3 ; extra == 'test'
Requires-Dist: pytest-cov >=5.0.0 ; extra == 'test'
